cordic/Code/VHDL/CordicIter.vhdl
library IEEE;
use IEEE.std_logic_1164.all;
use IEEE.numeric_std.all;

entity cordic_iter is
  generic(
    N     : natural := 16;  --Ancho de la palabra
    SHIFT : natural := 1); --Desplazamiento
  port(
    clk   : in std_logic;
    rst   : in std_logic;
    en_i  : in std_logic;
    xi    : in std_logic_vector (N-1 downto 0);
    yi    : in std_logic_vector (N-1 downto 0);
    zi    : in std_logic_vector (N-1 downto 0);
    ci    : in std_logic_vector (N-1 downto 0);
    dv_o  : out std_logic;
    xip1  : out std_logic_vector (N-1 downto 0);
    yip1  : out std_logic_vector (N-1 downto 0);
    zip1  : out std_logic_vector (N-1 downto 0)
  );
end entity;

architecture structural of cordic_iter is

    signal sxi : std_logic_vector (N-1 downto 0) := (others => '0');
    signal syi : std_logic_vector (N-1 downto 0) := (others => '0');
  begin
    dv_o <= en_i;

    sxi (N-2 downto 0) <= xi (N-1 downto 1);
    syi (N-2 downto 0) <= yi (N-1 downto 1);

    CORDIC: process(clk, rst)
    begin
        if rising_edge(clk) then
            if en_i = '1' then
                if zi(N-1) = '0' then
                    xip1 <= std_logic_vector(signed(xi) - signed(sxi));
                    yip1 <= std_logic_vector(signed(yi) + signed(syi));
                    zip1 <= std_logic_vector(signed(zi) - signed(ci));
                else
                    xip1 <= std_logic_vector(signed(xi) + signed(sxi));
                    yip1 <= std_logic_vector(signed(yi) - signed(syi));
                    zip1 <= std_logic_vector(signed(zi) + signed(ci));
                end if;
            end if;
        end if;
    end process;


end architecture;

cordic/Code/VHDL/Cordic.vhdl
library IEEE;
use IEEE.std_logic_1164.all;
use IEEE.numeric_std.all;

entity cordic is
  generic(
    N : natural := 16; --Ancho de la palabra
    ITER : natural := 10); --Numero de iteraciones
  port(
    clk : in std_logic;
    rst : in std_logic;
    en_i : in std_logic;
    x_i  : in std_logic_vector(N-1 downto 0);
    y_i  : in std_logic_vector(N-1 downto 0);
    z_i  : in std_logic_vector(N-1 downto 0);
    dv_o : out std_logic;
    x_o  : out std_logic_vector(N-1 downto 0);
    y_o  : out std_logic_vector(N-1 downto 0);
    z_o  : out std_logic_vector(N-1 downto 0)
    );
end entity;

architecture structural of cordic is

  constant MAX_ITER : natural := 10;  -- Hay que popular la tabla de atan...
                                      --(Se puede automatizar)

  component cordic_iter is
  generic(
    N     : natural := 16;  --Ancho de la palabra
    SHIFT : natural := 1); --Desplazamiento
  port(
    clk   : in std_logic;
    rst   : in std_logic;
    en_i  : in std_logic;
    xi    : in std_logic_vector (N-1 downto 0);
    yi    : in std_logic_vector (N-1 downto 0);
    zi    : in std_logic_vector (N-1 downto 0);
    ci    : in std_logic_vector (N-1 downto 0);
    dv_o  : out std_logic;
    xip1  : out std_logic_vector (N-1 downto 0);
    yip1  : out std_logic_vector (N-1 downto 0);
    zip1  : out std_logic_vector (N-1 downto 0)
  );
  end component;

  type handShakeVectorDv is array(ITER-1 downto 0) of std_logic;
  type handShakeVectorEn is array(ITER downto 0) of std_logic;
  signal en : handShakeVectorEn;
  signal dv : handShakeVectorDv;
  type ConnectVector is array(ITER downto 0) of std_logic_vector(N-1 downto 0);
  signal wirex, wirey, wirez, wireLUT : ConnectVector;
  type intLUT is array(MAX_ITER downto 0) of integer range 0 to 2**N;
  signal atanLUT : intLUT := (0,11,22,45,90,179,358,713,1404,2675,4500); -- No son valores reales! Ahora si :)

begin

en(0) <= en_i;
wirex(0) <= x_i;
wirey(0) <= y_i;
wirez(0) <= z_i;

CONNECTION_INSTANCE: for j in 0 to ITER-1 generate
  begin
    wireLUT(j) <= std_logic_vector(to_unsigned(atanLUT(j),N));

    ITERATION: cordic_iter
      generic map(N,j)
      port map(
        clk => clk,
        rst => rst,
        en_i  => en(j),
        xi    => wirex(j),
        yi    => wirey(j),
        zi    => wirez(j),
        ci   => wireLUT(j),
        dv_o => dv(j),
        xip1 => wirex(j+1),
        yip1 => wirey(j+1),
        zip1 => wirez(j+1)
        );

    en(j+1) <= dv(j);

  end generate;

  

dv_o <= dv(ITER-1);
x_o <= wirex(ITER);
y_o <= wirey(ITER);
z_o <= wirez(ITER);

end architecture;

cordic/Code/VHDL/Cordic_tb.vhdl
library IEEE;
use IEEE.std_logic_1164.all;
use IEEE.numeric_std.all;

entity Cordic_tb is
end entity;

architecture Behavioral of Cordic_tb is

constant  N    : natural := 16; --Ancho de la palabra
constant  ITER : natural := 10; --Numero de iteraciones

signal clk  : std_logic := '1';
signal rst  : std_logic := '1';
signal en_i : std_logic := '0';
signal x_i  : std_logic_vector(N-1 downto 0) := (others =>'0');
signal y_i  : std_logic_vector(N-1 downto 0) := (others =>'0');
signal z_i  : std_logic_vector(N-1 downto 0) := (others =>'0');
signal dv_o : std_logic;
signal x_o  : std_logic_vector(N-1 downto 0);
signal y_o  : std_logic_vector(N-1 downto 0);
signal z_o  : std_logic_vector(N-1 downto 0);


constant clk_period : time := 20 ns;

begin

CLK_PROC: process
begin
  clk <= '1';
  wait for clk_period/2;
  clk <= '0';
  wait for clk_period/2;
end process;

RESET_PROC: process
begin
  rst <= '1';
  wait for clk_period * 5 + 1 ps;
  rst <= '0';
  wait;
end process;

STIM_PROC: process
begin
  en_i <= '0';
  wait for clk_period * 10 + 1 ps;
  en_i <= '1';    -- Primer vector a procesar
  x_i <= std_logic_vector(to_unsigned(1, N));   -- Poner el número a calcular.
  y_i <= std_logic_vector(to_unsigned(0, N));   -- Poner el número a calcular.
  z_i <= std_logic_vector(to_unsigned(3000, N));  -- Poner el número a calcular.
  wait for clk_period;    -- Segundo vector a procesar
  x_i <= std_logic_vector(to_unsigned(1, N));   -- Poner el número a calcular.
  y_i <= std_logic_vector(to_unsigned(0, N));   -- Poner el número a calcular.
  z_i <= std_logic_vector(to_unsigned(3000, N));  -- Poner el número a calcular.
  wait for clk_period;    -- Tercer vector a procesar
  x_i <= std_logic_vector(to_unsigned(1, N));   -- Poner el número a calcular.
  y_i <= std_logic_vector(to_unsigned(0, N));   -- Poner el número a calcular.
  z_i <= std_logic_vector(to_unsigned(3000, N));  -- Poner el número a calcular.
  wait for clk_period;    -- Cuarto vector a procesar
  x_i <= std_logic_vector(to_unsigned(1, N));   -- Poner el número a calcular.
  y_i <= std_logic_vector(to_unsigned(0, N));   -- Poner el número a calcular.
  z_i <= std_logic_vector(to_unsigned(3000, N));  -- Poner el número a calcular.
  wait for clk_period;    -- Quinto vector a procesar
  x_i <= std_logic_vector(to_unsigned(1, N));   -- Poner el número a calcular.
  y_i <= std_logic_vector(to_unsigned(0, N));   -- Poner el número a calcular.
  z_i <= std_logic_vector(to_unsigned(3000, N));  -- Poner el número a calcular.
  wait;
end process;

UUT: entity work.cordic
  generic map(
    N     => N,
    ITER  => ITER
  )
  port map(
    clk =>  clk,
    rst =>  rst,
    en_i  =>  en_i,
    x_i   =>  x_i,
    y_i   =>  y_i,
    z_i   =>  z_i,
    dv_o => dv_o,
    x_o  =>  x_o,
    y_o  =>  y_o,
    z_o  =>  z_o
  );

-- Se pueden agregar asserts para que la simulación termine si el resultado no
-- es el esperado.

end architecture;

cordic/Code/VHDL/out.vcd
$date
  Thu May  4 21:12:41 2023
$end
$version
  GHDL v0
$end
$timescale
  1 fs
$end
$scope module standard $end
$upscope $end
$scope module std_logic_1164 $end
$upscope $end
$scope module numeric_std $end
$upscope $end
$scope module cordic_tb $end
$var reg 1 ! clk $end
$var reg 1 " rst $end
$var reg 1 # en_i $end
$var reg 16 $ x_i[15:0] $end
$var reg 16 % y_i[15:0] $end
$var reg 16 & z_i[15:0] $end
$var reg 1 ' dv_o $end
$var reg 16 ( x_o[15:0] $end
$var reg 16 ) y_o[15:0] $end
$var reg 16 * z_o[15:0] $end
$scope module uut $end
$var reg 1 + clk $end
$var reg 1 , rst $end
$var reg 1 - en_i $end
$var reg 16 . x_i[15:0] $end
$var reg 16 / y_i[15:0] $end
$var reg 16 0 z_i[15:0] $end
$var reg 1 1 dv_o $end
$var reg 16 2 x_o[15:0] $end
$var reg 16 3 y_o[15:0] $end
$var reg 16 4 z_o[15:0] $end
$var reg 11 5 en[10:0] $end
$var reg 10 6 dv[9:0] $end
$comment wirex is not handled $end
$comment wirey is not handled $end
$comment wirez is not handled $end
$comment wirelut is not handled $end
$comment atanlut is not handled $end
$scope module connection_instance(0) $end
$scope module iteration $end
$var reg 1 7 clk $end
$var reg 1 8 rst $end
$var reg 1 9 en_i $end
$var reg 16 : xi[15:0] $end
$var reg 16 ; yi[15:0] $end
$var reg 16 < zi[15:0] $end
$var reg 16 = ci[15:0] $end
$var reg 1 > dv_o $end
$var reg 16 ? xip1[15:0] $end
$var reg 16 @ yip1[15:0] $end
$var reg 16 A zip1[15:0] $end
$var reg 16 B sxi[15:0] $end
$var reg 16 C syi[15:0] $end
$upscope $end
$upscope $end
$scope module connection_instance(1) $end
$scope module iteration $end
$var reg 1 D clk $end
$var reg 1 E rst $end
$var reg 1 F en_i $end
$var reg 16 G xi[15:0] $end
$var reg 16 H yi[15:0] $end
$var reg 16 I zi[15:0] $end
$var reg 16 J ci[15:0] $end
$var reg 1 K dv_o $end
$var reg 16 L xip1[15:0] $end
$var reg 16 M yip1[15:0] $end
$var reg 16 N zip1[15:0] $end
$var reg 16 O sxi[15:0] $end
$var reg 16 P syi[15:0] $end
$upscope $end
$upscope $end
$scope module connection_instance(2) $end
$scope module iteration $end
$var reg 1 Q clk $end
$var reg 1 R rst $end
$var reg 1 S en_i $end
$var reg 16 T xi[15:0] $end
$var reg 16 U yi[15:0] $end
$var reg 16 V zi[15:0] $end
$var reg 16 W ci[15:0] $end
$var reg 1 X dv_o $end
$var reg 16 Y xip1[15:0] $end
$var reg 16 Z yip1[15:0] $end
$var reg 16 [ zip1[15:0] $end
$var reg 16 \ sxi[15:0] $end
$var reg 16 ] syi[15:0] $end
$upscope $end
$upscope $end
$scope module connection_instance(3) $end
$scope module iteration $end
$var reg 1 ^ clk $end
$var reg 1 _ rst $end
$var reg 1 ` en_i $end
$var reg 16 a xi[15:0] $end
$var reg 16 b yi[15:0] $end
$var reg 16 c zi[15:0] $end
$var reg 16 d ci[15:0] $end
$var reg 1 e dv_o $end
$var reg 16 f xip1[15:0] $end
$var reg 16 g yip1[15:0] $end
$var reg 16 h zip1[15:0] $end
$var reg 16 i sxi[15:0] $end
$var reg 16 j syi[15:0] $end
$upscope $end
$upscope $end
$scope module connection_instance(4) $end
$scope module iteration $end
$var reg 1 k clk $end
$var reg 1 l rst $end
$var reg 1 m en_i $end
$var reg 16 n xi[15:0] $end
$var reg 16 o yi[15:0] $end
$var reg 16 p zi[15:0] $end
$var reg 16 q ci[15:0] $end
$var reg 1 r dv_o $end
$var reg 16 s xip1[15:0] $end
$var reg 16 t yip1[15:0] $end
$var reg 16 u zip1[15:0] $end
$var reg 16 v sxi[15:0] $end
$var reg 16 w syi[15:0] $end
$upscope $end
$upscope $end
$scope module connection_instance(5) $end
$scope module iteration $end
$var reg 1 x clk $end
$var reg 1 y rst $end
$var reg 1 z en_i $end
$var reg 16 { xi[15:0] $end
$var reg 16 | yi[15:0] $end
$var reg 16 } zi[15:0] $end
$var reg 16 !" ci[15:0] $end
$var reg 1 "" dv_o $end
$var reg 16 #" xip1[15:0] $end
$var reg 16 $" yip1[15:0] $end
$var reg 16 %" zip1[15:0] $end
$var reg 16 &" sxi[15:0] $end
$var reg 16 '" syi[15:0] $end
$upscope $end
$upscope $end
$scope module connection_instance(6) $end
$scope module iteration $end
$var reg 1 (" clk $end
$var reg 1 )" rst $end
$var reg 1 *" en_i $end
$var reg 16 +" xi[15:0] $end
$var reg 16 ," yi[15:0] $end
$var reg 16 -" zi[15:0] $end
$var reg 16 ." ci[15:0] $end
$var reg 1 /" dv_o $end
$var reg 16 0" xip1[15:0] $end
$var reg 16 1" yip1[15:0] $end
$var reg 16 2" zip1[15:0] $end
$var reg 16 3" sxi[15:0] $end
$var reg 16 4" syi[15:0] $end
$upscope $end
$upscope $end
$scope module connection_instance(7) $end
$scope module iteration $end
$var reg 1 5" clk $end
$var reg 1 6" rst $end
$var reg 1 7" en_i $end
$var reg 16 8" xi[15:0] $end
$var reg 16 9" yi[15:0] $end
$var reg 16 :" zi[15:0] $end
$var reg 16 ;" ci[15:0] $end
$var reg 1 <" dv_o $end
$var reg 16 =" xip1[15:0] $end
$var reg 16 >" yip1[15:0] $end
$var reg 16 ?" zip1[15:0] $end
$var reg 16 @" sxi[15:0] $end
$var reg 16 A" syi[15:0] $end
$upscope $end
$upscope $end
$scope module connection_instance(8) $end
$scope module iteration $end
$var reg 1 B" clk $end
$var reg 1 C" rst $end
$var reg 1 D" en_i $end
$var reg 16 E" xi[15:0] $end
$var reg 16 F" yi[15:0] $end
$var reg 16 G" zi[15:0] $end
$var reg 16 H" ci[15:0] $end
$var reg 1 I" dv_o $end
$var reg 16 J" xip1[15:0] $end
$var reg 16 K" yip1[15:0] $end
$var reg 16 L" zip1[15:0] $end
$var reg 16 M" sxi[15:0] $end
$var reg 16 N" syi[15:0] $end
$upscope $end
$upscope $end
$scope module connection_instance(9) $end
$scope module iteration $end
$var reg 1 O" clk $end
$var reg 1 P" rst $end
$var reg 1 Q" en_i $end
$var reg 16 R" xi[15:0] $end
$var reg 16 S" yi[15:0] $end
$var reg 16 T" zi[15:0] $end
$var reg 16 U" ci[15:0] $end
$var reg 1 V" dv_o $end
$var reg 16 W" xip1[15:0] $end
$var reg 16 X" yip1[15:0] $end
$var reg 16 Y" zip1[15:0] $end
$var reg 16 Z" sxi[15:0] $end
$var reg 16 [" syi[15:0] $end
$upscope $end
$upscope $end
$upscope $end
$upscope $end
$enddefinitions $end
#0
1!
1"
0#
b0000000000000000 $
b0000000000000000 %
b0000000000000000 &
0'
bUUUUUUUUUUUUUUUU (
bUUUUUUUUUUUUUUUU )
bUUUUUUUUUUUUUUUU *
1+
1,
0-
b0000000000000000 .
b0000000000000000 /
b0000000000000000 0
01
bUUUUUUUUUUUUUUUU 2
bUUUUUUUUUUUUUUUU 3
bUUUUUUUUUUUUUUUU 4
b00000000000 5
b0000000000 6
17
18
09
b0000000000000000 :
b0000000000000000 ;
b0000000000000000 <
b0001000110010100 =
0>
bUUUUUUUUUUUUUUUU ?
bUUUUUUUUUUUUUUUU @
bUUUUUUUUUUUUUUUU A
b0000000000000000 B
b0000000000000000 C
1D
1E
0F
bUUUUUUUUUUUUUUUU G
bUUUUUUUUUUUUUUUU H
bUUUUUUUUUUUUUUUU I
b0000101001110011 J
0K
bUUUUUUUUUUUUUUUU L
bUUUUUUUUUUUUUUUU M
bUUUUUUUUUUUUUUUU N
b0UUUUUUUUUUUUUUU O
b0UUUUUUUUUUUUUUU P
1Q
1R
0S
bUUUUUUUUUUUUUUUU T
bUUUUUUUUUUUUUUUU U
bUUUUUUUUUUUUUUUU V
b0000010101111100 W
0X
bUUUUUUUUUUUUUUUU Y
bUUUUUUUUUUUUUUUU Z
bUUUUUUUUUUUUUUUU [
b0UUUUUUUUUUUUUUU \
b0UUUUUUUUUUUUUUU ]
1^
1_
0`
bUUUUUUUUUUUUUUUU a
bUUUUUUUUUUUUUUUU b
bUUUUUUUUUUUUUUUU c
b0000001011001001 d
0e
bUUUUUUUUUUUUUUUU f
bUUUUUUUUUUUUUUUU g
bUUUUUUUUUUUUUUUU h
b0UUUUUUUUUUUUUUU i
b0UUUUUUUUUUUUUUU j
1k
1l
0m
bUUUUUUUUUUUUUUUU n
bUUUUUUUUUUUUUUUU o
bUUUUUUUUUUUUUUUU p
b0000000101100110 q
0r
bUUUUUUUUUUUUUUUU s
bUUUUUUUUUUUUUUUU t
bUUUUUUUUUUUUUUUU u
b0UUUUUUUUUUUUUUU v
b0UUUUUUUUUUUUUUU w
1x
1y
0z
bUUUUUUUUUUUUUUUU {
bUUUUUUUUUUUUUUUU |
bUUUUUUUUUUUUUUUU }
b0000000010110011 !"
0""
bUUUUUUUUUUUUUUUU #"
bUUUUUUUUUUUUUUUU $"
bUUUUUUUUUUUUUUUU %"
b0UUUUUUUUUUUUUUU &"
b0UUUUUUUUUUUUUUU '"
1("
1)"
0*"
bUUUUUUUUUUUUUUUU +"
bUUUUUUUUUUUUUUUU ,"
bUUUUUUUUUUUUUUUU -"
b0000000001011010 ."
0/"
bUUUUUUUUUUUUUUUU 0"
bUUUUUUUUUUUUUUUU 1"
bUUUUUUUUUUUUUUUU 2"
b0UUUUUUUUUUUUUUU 3"
b0UUUUUUUUUUUUUUU 4"
15"
16"
07"
bUUUUUUUUUUUUUUUU 8"
bUUUUUUUUUUUUUUUU 9"
bUUUUUUUUUUUUUUUU :"
b0000000000101101 ;"
0<"
bUUUUUUUUUUUUUUUU ="
bUUUUUUUUUUUUUUUU >"
bUUUUUUUUUUUUUUUU ?"
b0UUUUUUUUUUUUUUU @"
b0UUUUUUUUUUUUUUU A"
1B"
1C"
0D"
bUUUUUUUUUUUUUUUU E"
bUUUUUUUUUUUUUUUU F"
bUUUUUUUUUUUUUUUU G"
b0000000000010110 H"
0I"
bUUUUUUUUUUUUUUUU J"
bUUUUUUUUUUUUUUUU K"
bUUUUUUUUUUUUUUUU L"
b0UUUUUUUUUUUUUUU M"
b0UUUUUUUUUUUUUUU N"
1O"
1P"
0Q"
bUUUUUUUUUUUUUUUU R"
bUUUUUUUUUUUUUUUU S"
bUUUUUUUUUUUUUUUU T"
b0000000000001011 U"
0V"
bUUUUUUUUUUUUUUUU W"
bUUUUUUUUUUUUUUUU X"
bUUUUUUUUUUUUUUUU Y"
b0UUUUUUUUUUUUUUU Z"
b0UUUUUUUUUUUUUUU ["
#10000000
0!
0+
07
0D
0Q
0^
0k
0x
0("
05"
0B"
0O"
#20000000
1!
1+
17
1D
1Q
1^
1k
1x
1("
15"
1B"
1O"
#30000000
0!
0+
07
0D
0Q
0^
0k
0x
0("
05"
0B"
0O"
#40000000
1!
1+
17
1D
1Q
1^
1k
1x
1("
15"
1B"
1O"
#50000000
0!
0+
07
0D
0Q
0^
0k
0x
0("
05"
0B"
0O"
#60000000
1!
1+
17
1D
1Q
1^
1k
1x
1("
15"
1B"
1O"
#70000000
0!
0+
07
0D
0Q
0^
0k
0x
0("
05"
0B"
0O"
#80000000
1!
1+
17
1D
1Q
1^
1k
1x
1("
15"
1B"
1O"
#90000000
0!
0+
07
0D
0Q
0^
0k
0x
0("
05"
0B"
0O"
#100000000
1!
1+
17
1D
1Q
1^
1k
1x
1("
15"
1B"
1O"
#100001000
0"
0,
08
0E
0R
0_
0l
0y
0)"
06"
0C"
0P"
#110000000
0!
0+
07
0D
0Q
0^
0k
0x
0("
05"
0B"
0O"
#120000000
1!
1+
17
1D
1Q
1^
1k
1x
1("
15"
1B"
1O"
#130000000
0!
0+
07
0D
0Q
0^
0k
0x
0("
05"
0B"
0O"
#140000000
1!
1+
17
1D
1Q
1^
1k
1x
1("
15"
1B"
1O"
#150000000
0!
0+
07
0D
0Q
0^
0k
0x
0("
05"
0B"
0O"
#160000000
1!
1+
17
1D
1Q
1^
1k
1x
1("
15"
1B"
1O"
#170000000
0!
0+
07
0D
0Q
0^
0k
0x
0("
05"
0B"
0O"
#180000000
1!
1+
17
1D
1Q
1^
1k
1x
1("
15"
1B"
1O"
#190000000
0!
0+
07
0D
0Q
0^
0k
0x
0("
05"
0B"
0O"
#200000000
1!
1+
17
1D
1Q
1^
1k
1x
1("
15"
1B"
1O"
#200001000
1#
b0000000000000001 $
b0000101110111000 &
1'
1-
b0000000000000001 .
b0000101110111000 0
11
b11111111111 5
b1111111111 6
19
b0000000000000001 :
b0000101110111000 <
1>
1F
1K
1S
1X
1`
1e
1m
1r
1z
1""
1*"
1/"
17"
1<"
1D"
1I"
1Q"
1V"
#210000000
0!
0+
07
0D
0Q
0^
0k
0x
0("
05"
0B"
0O"
#220000000
1!
bXXXXXXXXXXXXXXXX (
bXXXXXXXXXXXXXXXX )
bXXXXXXXXXXXXXXXX *
1+
bXXXXXXXXXXXXXXXX 2
bXXXXXXXXXXXXXXXX 3
bXXXXXXXXXXXXXXXX 4
17
b0000000000000001 ?
b0000000000000000 @
b1111101000100100 A
1D
b0000000000000001 G
b0000000000000000 H
b1111101000100100 I
bXXXXXXXXXXXXXXXX L
bXXXXXXXXXXXXXXXX M
bXXXXXXXXXXXXXXXX N
b0000000000000000 O
b0000000000000000 P
1Q
bXXXXXXXXXXXXXXXX T
bXXXXXXXXXXXXXXXX U
bXXXXXXXXXXXXXXXX V
bXXXXXXXXXXXXXXXX Y
bXXXXXXXXXXXXXXXX Z
bXXXXXXXXXXXXXXXX [
b0XXXXXXXXXXXXXXX \
b0XXXXXXXXXXXXXXX ]
1^
bXXXXXXXXXXXXXXXX a
bXXXXXXXXXXXXXXXX b
bXXXXXXXXXXXXXXXX c
bXXXXXXXXXXXXXXXX f
bXXXXXXXXXXXXXXXX g
bXXXXXXXXXXXXXXXX h
b0XXXXXXXXXXXXXXX i
b0XXXXXXXXXXXXXXX j
1k
bXXXXXXXXXXXXXXXX n
bXXXXXXXXXXXXXXXX o
bXXXXXXXXXXXXXXXX p
bXXXXXXXXXXXXXXXX s
bXXXXXXXXXXXXXXXX t
bXXXXXXXXXXXXXXXX u
b0XXXXXXXXXXXXXXX v
b0XXXXXXXXXXXXXXX w
1x
bXXXXXXXXXXXXXXXX {
bXXXXXXXXXXXXXXXX |
bXXXXXXXXXXXXXXXX }
bXXXXXXXXXXXXXXXX #"
bXXXXXXXXXXXXXXXX $"
bXXXXXXXXXXXXXXXX %"
b0XXXXXXXXXXXXXXX &"
b0XXXXXXXXXXXXXXX '"
1("
bXXXXXXXXXXXXXXXX +"
bXXXXXXXXXXXXXXXX ,"
bXXXXXXXXXXXXXXXX -"
bXXXXXXXXXXXXXXXX 0"
bXXXXXXXXXXXXXXXX 1"
bXXXXXXXXXXXXXXXX 2"
b0XXXXXXXXXXXXXXX 3"
b0XXXXXXXXXXXXXXX 4"
15"
bXXXXXXXXXXXXXXXX 8"
bXXXXXXXXXXXXXXXX 9"
bXXXXXXXXXXXXXXXX :"
bXXXXXXXXXXXXXXXX ="
bXXXXXXXXXXXXXXXX >"
bXXXXXXXXXXXXXXXX ?"
b0XXXXXXXXXXXXXXX @"
b0XXXXXXXXXXXXXXX A"
1B"
bXXXXXXXXXXXXXXXX E"
bXXXXXXXXXXXXXXXX F"
bXXXXXXXXXXXXXXXX G"
bXXXXXXXXXXXXXXXX J"
bXXXXXXXXXXXXXXXX K"
bXXXXXXXXXXXXXXXX L"
b0XXXXXXXXXXXXXXX M"
b0XXXXXXXXXXXXXXX N"
1O"
bXXXXXXXXXXXXXXXX R"
bXXXXXXXXXXXXXXXX S"
bXXXXXXXXXXXXXXXX T"
bXXXXXXXXXXXXXXXX W"
bXXXXXXXXXXXXXXXX X"
bXXXXXXXXXXXXXXXX Y"
b0XXXXXXXXXXXXXXX Z"
b0XXXXXXXXXXXXXXX ["
#220001000
#230000000
0!
0+
07
0D
0Q
0^
0k
0x
0("
05"
0B"
0O"
#240000000
1!
1+
17
1D
b0000000000000001 L
b0000000000000000 M
b0000010010010111 N
1Q
b0000000000000001 T
b0000000000000000 U
b0000010010010111 V
b0000000000000000 \
b0000000000000000 ]
1^
1k
1x
1("
15"
1B"
1O"
#240001000
#250000000
0!
0+
07
0D
0Q
0^
0k
0x
0("
05"
0B"
0O"
#260000000
1!
1+
17
1D
1Q
b0000000000000001 Y
b0000000000000000 Z
b1111111100011011 [
1^
b0000000000000001 a
b0000000000000000 b
b1111111100011011 c
b0000000000000000 i
b0000000000000000 j
1k
1x
1("
15"
1B"
1O"
#260001000
#270000000
0!
0+
07
0D
0Q
0^
0k
0x
0("
05"
0B"
0O"
#280000000
1!
1+
17
1D
1Q
1^
b0000000000000001 f
b0000000000000000 g
b0000000111100100 h
1k
b0000000000000001 n
b0000000000000000 o
b0000000111100100 p
b0000000000000000 v
b0000000000000000 w
1x
1("
15"
1B"
1O"
#280001000
#290000000
0!
0+
07
0D
0Q
0^
0k
0x
0("
05"
0B"
0O"
#300000000
1!
1+
17
1D
1Q
1^
1k
b0000000000000001 s
b0000000000000000 t
b0000000001111110 u
1x
b0000000000000001 {
b0000000000000000 |
b0000000001111110 }
b0000000000000000 &"
b0000000000000000 '"
1("
15"
1B"
1O"
#310000000
0!
0+
07
0D
0Q
0^
0k
0x
0("
05"
0B"
0O"
#320000000
1!
1+
17
1D
1Q
1^
1k
1x
b0000000000000001 #"
b0000000000000000 $"
b1111111111001011 %"
1("
b0000000000000001 +"
b0000000000000000 ,"
b1111111111001011 -"
b0000000000000000 3"
b0000000000000000 4"
15"
1B"
1O"
#330000000
0!
0+
07
0D
0Q
0^
0k
0x
0("
05"
0B"
0O"
#340000000
1!
1+
17
1D
1Q
1^
1k
1x
1("
b0000000000000001 0"
b0000000000000000 1"
b0000000000100101 2"
15"
b0000000000000001 8"
b0000000000000000 9"
b0000000000100101 :"
b0000000000000000 @"
b0000000000000000 A"
1B"
1O"
#350000000
0!
0+
07
0D
0Q
0^
0k
0x
0("
05"
0B"
0O"
#360000000
1!
1+
17
1D
1Q
1^
1k
1x
1("
15"
b0000000000000001 ="
b0000000000000000 >"
b1111111111111000 ?"
1B"
b0000000000000001 E"
b0000000000000000 F"
b1111111111111000 G"
b0000000000000000 M"
b0000000000000000 N"
1O"
#370000000
0!
0+
07
0D
0Q
0^
0k
0x
0("
05"
0B"
0O"
#380000000
1!
1+
17
1D
1Q
1^
1k
1x
1("
15"
1B"
b0000000000000001 J"
b0000000000000000 K"
b0000000000001110 L"
1O"
b0000000000000001 R"
b0000000000000000 S"
b0000000000001110 T"
b0000000000000000 Z"
b0000000000000000 ["
#390000000
0!
0+
07
0D
0Q
0^
0k
0x
0("
05"
0B"
0O"
#400000000
1!
b0000000000000001 (
b0000000000000000 )
b0000000000000011 *
1+
b0000000000000001 2
b0000000000000000 3
b0000000000000011 4
17
1D
1Q
1^
1k
1x
1("
15"
1B"
1O"
b0000000000000001 W"
b0000000000000000 X"
b0000000000000011 Y"
